lmfuser/__init__.py
lmfuser/model_loader.py
lmfuser/optimizers.py
lmfuser/schedulers.py
lmfuser/task.py
lmfuser/utils.py
lmfuser/runners/__init__.py
lmfuser/runners/ddp_runner.py
lmfuser/runners/runner.py
lmfuser-0.1.2.dist-info/METADATA
lmfuser-0.1.2.dist-info/WHEEL
lmfuser-0.1.2.dist-info/licenses/LICENSE
lmfuser-0.1.2.dist-info/RECORD
