Metadata-Version: 2.4
Name: LMFuser
Version: 0.1.2
Summary: The LMFuser training framework.
Project-URL: Homepage, https://github.com/TYTTYTTYT/LMFuser
Project-URL: Documentation, https://github.com/TYTTYTTYT/LMFuser
Project-URL: Repository, https://github.com/TYTTYTTYT/LMFuser
Project-URL: Bug Tracker, https://github.com/TYTTYTTYT/LMFuser
Project-URL: Changelog, https://github.com/TYTTYTTYT/LMFuser
Author-email: Yintao Tai <tai.yintao@gmail.com>
Maintainer-email: Yintao Tai <tai.yintao@gmail.com>
License-File: LICENSE
Keywords: machine learning,pytorch
Classifier: Intended Audience :: Information Technology
Classifier: Intended Audience :: Science/Research
Classifier: Programming Language :: Python :: 3 :: Only
Classifier: Topic :: Utilities
Requires-Python: >=3.11
Requires-Dist: hyperargs>=0.1.3
Requires-Dist: lmfuser-data>=0.1.1
Requires-Dist: numpy
Requires-Dist: pandas
Requires-Dist: pyarrow
Requires-Dist: torch>=2.4.0
Requires-Dist: tqdm
Requires-Dist: wandb
